{"openapi":"3.1.0","info":{"title":"FastAPI","version":"0.1.0"},"paths":{"/api/v1/courses/":{"get":{"tags":["courses"],"summary":"Read Courses","operationId":"read_courses_api_v1_courses__get","parameters":[{"name":"offset","in":"query","required":false,"schema":{"type":"integer","default":0,"title":"Offset"}},{"name":"limit","in":"query","required":false,"schema":{"type":"integer","default":100,"title":"Limit"}}],"responses":{"200":{"description":"Successful Response","content":{"application/json":{"schema":{"$ref":"#/components/schemas/CoursesPublic"}}}},"422":{"description":"Validation Error","content":{"application/json":{"schema":{"$ref":"#/components/schemas/HTTPValidationError"}}}}}},"post":{"tags":["courses"],"summary":"Create Course","operationId":"create_course_api_v1_courses__post","security":[{"OAuth2PasswordBearer":[]}],"requestBody":{"required":true,"content":{"application/json":{"schema":{"$ref":"#/components/schemas/CourseCreate"}}}},"responses":{"200":{"description":"Successful Response","content":{"application/json":{"schema":{"$ref":"#/components/schemas/CoursePublic"}}}},"422":{"description":"Validation Error","content":{"application/json":{"schema":{"$ref":"#/components/schemas/HTTPValidationError"}}}}}}},"/api/v1/courses/{id}":{"get":{"tags":["courses"],"summary":"Read Course","operationId":"read_course_api_v1_courses__id__get","parameters":[{"name":"id","in":"path","required":true,"schema":{"type":"string","format":"uuid","title":"Id"}}],"responses":{"200":{"description":"Successful Response","content":{"application/json":{"schema":{"$ref":"#/components/schemas/CoursePublic"}}}},"422":{"description":"Validation Error","content":{"application/json":{"schema":{"$ref":"#/components/schemas/HTTPValidationError"}}}}}},"put":{"tags":["courses"],"summary":"Update Course","operationId":"update_course_api_v1_courses__id__put","security":[{"OAuth2PasswordBearer":[]}],"parameters":[{"name":"id","in":"path","required":true,"schema":{"type":"string","format":"uuid","title":"Id"}}],"requestBody":{"required":true,"content":{"application/json":{"schema":{"$ref":"#/components/schemas/CourseUpdate"}}}},"responses":{"200":{"description":"Successful Response","content":{"application/json":{"schema":{"$ref":"#/components/schemas/CoursePublic"}}}},"422":{"description":"Validation Error","content":{"application/json":{"schema":{"$ref":"#/components/schemas/HTTPValidationError"}}}}}},"delete":{"tags":["courses"],"summary":"Delete Course","operationId":"delete_course_api_v1_courses__id__delete","security":[{"OAuth2PasswordBearer":[]}],"parameters":[{"name":"id","in":"path","required":true,"schema":{"type":"string","format":"uuid","title":"Id"}}],"responses":{"200":{"description":"Successful Response","content":{"application/json":{"schema":{"title":"Response Delete Course Api V1 Courses  Id  Delete"}}}},"422":{"description":"Validation Error","content":{"application/json":{"schema":{"$ref":"#/components/schemas/HTTPValidationError"}}}}}}},"/api/v1/profs/":{"get":{"tags":["professors"],"summary":"Read Profs","operationId":"read_profs_api_v1_profs__get","parameters":[{"name":"offset","in":"query","required":false,"schema":{"type":"integer","default":0,"title":"Offset"}},{"name":"limit","in":"query","required":false,"schema":{"type":"integer","default":100,"title":"Limit"}}],"responses":{"200":{"description":"Successful Response","content":{"application/json":{"schema":{"$ref":"#/components/schemas/ProfsPublic"}}}},"422":{"description":"Validation Error","content":{"application/json":{"schema":{"$ref":"#/components/schemas/HTTPValidationError"}}}}}},"post":{"tags":["professors"],"summary":"Create Prof","operationId":"create_prof_api_v1_profs__post","security":[{"OAuth2PasswordBearer":[]}],"requestBody":{"required":true,"content":{"application/json":{"schema":{"$ref":"#/components/schemas/ProfCreate"}}}},"responses":{"200":{"description":"Successful Response","content":{"application/json":{"schema":{"$ref":"#/components/schemas/ProfPublic"}}}},"422":{"description":"Validation Error","content":{"application/json":{"schema":{"$ref":"#/components/schemas/HTTPValidationError"}}}}}}},"/api/v1/profs/{id}":{"get":{"tags":["professors"],"summary":"Read Prof","operationId":"read_prof_api_v1_profs__id__get","parameters":[{"name":"id","in":"path","required":true,"schema":{"type":"string","format":"uuid","title":"Id"}}],"responses":{"200":{"description":"Successful Response","content":{"application/json":{"schema":{"$ref":"#/components/schemas/ProfPublic"}}}},"422":{"description":"Validation Error","content":{"application/json":{"schema":{"$ref":"#/components/schemas/HTTPValidationError"}}}}}},"put":{"tags":["professors"],"summary":"Update Prof","operationId":"update_prof_api_v1_profs__id__put","security":[{"OAuth2PasswordBearer":[]}],"parameters":[{"name":"id","in":"path","required":true,"schema":{"type":"string","format":"uuid","title":"Id"}}],"requestBody":{"required":true,"content":{"application/json":{"schema":{"$ref":"#/components/schemas/ProfUpdate"}}}},"responses":{"200":{"description":"Successful Response","content":{"application/json":{"schema":{"$ref":"#/components/schemas/ProfPublic"}}}},"422":{"description":"Validation Error","content":{"application/json":{"schema":{"$ref":"#/components/schemas/HTTPValidationError"}}}}}},"delete":{"tags":["professors"],"summary":"Delete Prof","operationId":"delete_prof_api_v1_profs__id__delete","security":[{"OAuth2PasswordBearer":[]}],"parameters":[{"name":"id","in":"path","required":true,"schema":{"type":"string","format":"uuid","title":"Id"}}],"responses":{"200":{"description":"Successful Response","content":{"application/json":{"schema":{"title":"Response Delete Prof Api V1 Profs  Id  Delete"}}}},"422":{"description":"Validation Error","content":{"application/json":{"schema":{"$ref":"#/components/schemas/HTTPValidationError"}}}}}}},"/api/v1/chats/":{"get":{"tags":["chats"],"summary":"Read Chats","operationId":"read_chats_api_v1_chats__get","security":[{"OAuth2PasswordBearer":[]}],"parameters":[{"name":"offset","in":"query","required":false,"schema":{"type":"integer","default":0,"title":"Offset"}},{"name":"limit","in":"query","required":false,"schema":{"type":"integer","default":20,"title":"Limit"}}],"responses":{"200":{"description":"Successful Response","content":{"application/json":{"schema":{"$ref":"#/components/schemas/ChatsPublic"}}}},"422":{"description":"Validation Error","content":{"application/json":{"schema":{"$ref":"#/components/schemas/HTTPValidationError"}}}}}},"post":{"tags":["chats"],"summary":"Create Chat","operationId":"create_chat_api_v1_chats__post","security":[{"OAuth2PasswordBearer":[]}],"requestBody":{"required":true,"content":{"application/json":{"schema":{"$ref":"#/components/schemas/ChatCreate"}}}},"responses":{"200":{"description":"Successful Response","content":{"application/json":{"schema":{"$ref":"#/components/schemas/ChatPublic"}}}},"422":{"description":"Validation Error","content":{"application/json":{"schema":{"$ref":"#/components/schemas/HTTPValidationError"}}}}}}},"/api/v1/chats/{id}":{"get":{"tags":["chats"],"summary":"Read Chat","operationId":"read_chat_api_v1_chats__id__get","parameters":[{"name":"id","in":"path","required":true,"schema":{"type":"string","format":"uuid","title":"Id"}}],"responses":{"200":{"description":"Successful Response","content":{"application/json":{"schema":{"$ref":"#/components/schemas/ChatPublic"}}}},"422":{"description":"Validation Error","content":{"application/json":{"schema":{"$ref":"#/components/schemas/HTTPValidationError"}}}}}},"put":{"tags":["chats"],"summary":"Update Chat","operationId":"update_chat_api_v1_chats__id__put","security":[{"OAuth2PasswordBearer":[]}],"parameters":[{"name":"id","in":"path","required":true,"schema":{"type":"string","format":"uuid","title":"Id"}}],"requestBody":{"required":true,"content":{"application/json":{"schema":{"$ref":"#/components/schemas/ChatUpdate"}}}},"responses":{"200":{"description":"Successful Response","content":{"application/json":{"schema":{"$ref":"#/components/schemas/ChatPublic"}}}},"422":{"description":"Validation Error","content":{"application/json":{"schema":{"$ref":"#/components/schemas/HTTPValidationError"}}}}}},"delete":{"tags":["chats"],"summary":"Delete Chat","operationId":"delete_chat_api_v1_chats__id__delete","security":[{"OAuth2PasswordBearer":[]}],"parameters":[{"name":"id","in":"path","required":true,"schema":{"type":"string","format":"uuid","title":"Id"}}],"responses":{"200":{"description":"Successful Response","content":{"application/json":{"schema":{"title":"Response Delete Chat Api V1 Chats  Id  Delete"}}}},"422":{"description":"Validation Error","content":{"application/json":{"schema":{"$ref":"#/components/schemas/HTTPValidationError"}}}}}},"post":{"tags":["chats"],"summary":"Create Message","operationId":"create_message_api_v1_chats__id__post","security":[{"OAuth2PasswordBearer":[]}],"parameters":[{"name":"id","in":"path","required":true,"schema":{"type":"string","format":"uuid","title":"Id"}}],"requestBody":{"required":true,"content":{"application/json":{"schema":{"$ref":"#/components/schemas/MessageCreate"}}}},"responses":{"200":{"description":"Successful Response","content":{"application/json":{"schema":{"$ref":"#/components/schemas/MessagePublic"}}}},"422":{"description":"Validation Error","content":{"application/json":{"schema":{"$ref":"#/components/schemas/HTTPValidationError"}}}}}}},"/api/v1/chats/{id}/messages":{"get":{"tags":["chats"],"summary":"Read Messages","operationId":"read_messages_api_v1_chats__id__messages_get","security":[{"OAuth2PasswordBearer":[]}],"parameters":[{"name":"id","in":"path","required":true,"schema":{"type":"string","format":"uuid","title":"Id"}},{"name":"skip","in":"query","required":false,"schema":{"type":"integer","default":0,"title":"Skip"}},{"name":"limit","in":"query","required":false,"schema":{"type":"integer","default":20,"title":"Limit"}}],"responses":{"200":{"description":"Successful Response","content":{"application/json":{"schema":{"$ref":"#/components/schemas/MessagesPublic"}}}},"422":{"description":"Validation Error","content":{"application/json":{"schema":{"$ref":"#/components/schemas/HTTPValidationError"}}}}}}},"/api/v1/login/access-token":{"post":{"tags":["login","login"],"summary":"Login Access Token","description":"OAuth2 compatible token login, get an access token for future requests","operationId":"login_access_token_api_v1_login_access_token_post","requestBody":{"content":{"application/x-www-form-urlencoded":{"schema":{"$ref":"#/components/schemas/Body_login_access_token_api_v1_login_access_token_post"}}},"required":true},"responses":{"200":{"description":"Successful Response","content":{"application/json":{"schema":{"$ref":"#/components/schemas/Token"}}}},"422":{"description":"Validation Error","content":{"application/json":{"schema":{"$ref":"#/components/schemas/HTTPValidationError"}}}}}}},"/api/v1/signup":{"post":{"tags":["login","login"],"summary":"Register User","description":"Create new user without the need to be logged in.","operationId":"register_user_api_v1_signup_post","requestBody":{"content":{"application/json":{"schema":{"$ref":"#/components/schemas/UserRegister"}}},"required":true},"responses":{"200":{"description":"Successful Response","content":{"application/json":{"schema":{"$ref":"#/components/schemas/UserPublic"}}}},"422":{"description":"Validation Error","content":{"application/json":{"schema":{"$ref":"#/components/schemas/HTTPValidationError"}}}}}}}},"components":{"schemas":{"Body_login_access_token_api_v1_login_access_token_post":{"properties":{"grant_type":{"anyOf":[{"type":"string","pattern":"^password$"},{"type":"null"}],"title":"Grant Type"},"username":{"type":"string","title":"Username"},"password":{"type":"string","format":"password","title":"Password"},"scope":{"type":"string","title":"Scope","default":""},"client_id":{"anyOf":[{"type":"string"},{"type":"null"}],"title":"Client Id"},"client_secret":{"anyOf":[{"type":"string"},{"type":"null"}],"format":"password","title":"Client Secret"}},"type":"object","required":["username","password"],"title":"Body_login_access_token_api_v1_login_access_token_post"},"ChatCreate":{"properties":{"title":{"type":"string","maxLength":255,"minLength":1,"title":"Title"}},"type":"object","required":["title"],"title":"ChatCreate"},"ChatPublic":{"properties":{"title":{"type":"string","maxLength":255,"minLength":1,"title":"Title"},"id":{"type":"string","format":"uuid","title":"Id"}},"type":"object","required":["title","id"],"title":"ChatPublic"},"ChatUpdate":{"properties":{"title":{"anyOf":[{"type":"string","maxLength":255,"minLength":1},{"type":"null"}],"title":"Title"},"pinned":{"anyOf":[{"type":"boolean"},{"type":"null"}],"title":"Pinned","default":false}},"type":"object","title":"ChatUpdate"},"ChatsPublic":{"properties":{"data":{"items":{"$ref":"#/components/schemas/ChatPublic"},"type":"array","title":"Data"},"count":{"type":"integer","title":"Count"}},"type":"object","required":["data","count"],"title":"ChatsPublic"},"CourseCreate":{"properties":{"code":{"anyOf":[{"type":"string"},{"type":"null"}],"title":"Code"},"name":{"type":"string","title":"Name"}},"type":"object","required":["code","name"],"title":"CourseCreate"},"CoursePublic":{"properties":{"code":{"anyOf":[{"type":"string"},{"type":"null"}],"title":"Code"},"name":{"type":"string","title":"Name"},"course_id":{"type":"string","format":"uuid","title":"Course Id"}},"type":"object","required":["code","name","course_id"],"title":"CoursePublic"},"CourseUpdate":{"properties":{"code":{"anyOf":[{"type":"string"},{"type":"null"}],"title":"Code"},"name":{"anyOf":[{"type":"string"},{"type":"null"}],"title":"Name"}},"type":"object","required":["code","name"],"title":"CourseUpdate"},"CoursesPublic":{"properties":{"data":{"items":{"$ref":"#/components/schemas/CoursePublic"},"type":"array","title":"Data"},"count":{"type":"integer","title":"Count"}},"type":"object","required":["data","count"],"title":"CoursesPublic"},"HTTPValidationError":{"properties":{"detail":{"items":{"$ref":"#/components/schemas/ValidationError"},"type":"array","title":"Detail"}},"type":"object","title":"HTTPValidationError"},"MessageCreate":{"properties":{"content":{"type":"string","title":"Content"},"role":{"$ref":"#/components/schemas/MessageRole","default":"user"}},"type":"object","required":["content"],"title":"MessageCreate"},"MessagePublic":{"properties":{"content":{"type":"string","title":"Content"},"role":{"$ref":"#/components/schemas/MessageRole","default":"user"},"id":{"type":"string","format":"uuid","title":"Id"}},"type":"object","required":["content","id"],"title":"MessagePublic"},"MessageRole":{"type":"string","enum":["user","assistant","system"],"title":"MessageRole"},"MessagesPublic":{"properties":{"data":{"items":{"$ref":"#/components/schemas/MessagePublic"},"type":"array","title":"Data"},"count":{"type":"integer","title":"Count"}},"type":"object","required":["data","count"],"title":"MessagesPublic"},"ProfCreate":{"properties":{"name":{"type":"string","title":"Name"},"university":{"anyOf":[{"type":"string"},{"type":"null"}],"title":"University"},"academic_rank":{"anyOf":[{"type":"string"},{"type":"null"}],"title":"Academic Rank"},"average_rating":{"anyOf":[{"type":"number","maximum":5.0,"minimum":1.0},{"type":"string","pattern":"^(?!^[-+.]*$)[+-]?0*(?:\\d{0,0}|(?=[\\d.]{1,2}0*$)\\d{0,0}\\.\\d{0,2}0*$)"},{"type":"null"}],"title":"Average Rating","default":0}},"type":"object","required":["name","university","academic_rank"],"title":"ProfCreate"},"ProfPublic":{"properties":{"name":{"type":"string","title":"Name"},"university":{"anyOf":[{"type":"string"},{"type":"null"}],"title":"University"},"academic_rank":{"anyOf":[{"type":"string"},{"type":"null"}],"title":"Academic Rank"},"average_rating":{"anyOf":[{"type":"string","pattern":"^(?!^[-+.]*$)[+-]?0*(?:\\d{0,0}|(?=[\\d.]{1,2}0*$)\\d{0,0}\\.\\d{0,2}0*$)"},{"type":"null"}],"title":"Average Rating","default":0},"id":{"type":"string","format":"uuid","title":"Id"}},"type":"object","required":["name","university","academic_rank","id"],"title":"ProfPublic"},"ProfUpdate":{"properties":{"name":{"anyOf":[{"type":"string"},{"type":"null"}],"title":"Name"},"university":{"anyOf":[{"type":"string"},{"type":"null"}],"title":"University"},"academic_rank":{"anyOf":[{"type":"string"},{"type":"null"}],"title":"Academic Rank"},"average_rating":{"anyOf":[{"type":"number","maximum":5.0,"minimum":1.0},{"type":"string","pattern":"^(?!^[-+.]*$)[+-]?0*(?:\\d{0,0}|(?=[\\d.]{1,2}0*$)\\d{0,0}\\.\\d{0,2}0*$)"},{"type":"null"}],"title":"Average Rating","default":0}},"type":"object","required":["name","university","academic_rank"],"title":"ProfUpdate"},"ProfsPublic":{"properties":{"data":{"items":{"$ref":"#/components/schemas/ProfPublic"},"type":"array","title":"Data"},"count":{"type":"integer","title":"Count"}},"type":"object","required":["data","count"],"title":"ProfsPublic"},"Token":{"properties":{"access_token":{"type":"string","title":"Access Token"},"token_type":{"type":"string","title":"Token Type","default":"bearer"}},"type":"object","required":["access_token"],"title":"Token"},"UserPublic":{"properties":{"email":{"type":"string","maxLength":255,"format":"email","title":"Email"},"is_active":{"type":"boolean","title":"Is Active","default":true},"is_superuser":{"type":"boolean","title":"Is Superuser","default":false},"full_name":{"anyOf":[{"type":"string","maxLength":255},{"type":"null"}],"title":"Full Name"},"id":{"type":"string","format":"uuid","title":"Id"},"created_at":{"anyOf":[{"type":"string","format":"date-time"},{"type":"null"}],"title":"Created At"}},"type":"object","required":["email","id"],"title":"UserPublic"},"UserRegister":{"properties":{"email":{"type":"string","maxLength":255,"format":"email","title":"Email"},"password":{"type":"string","maxLength":128,"minLength":8,"title":"Password"},"full_name":{"anyOf":[{"type":"string","maxLength":255},{"type":"null"}],"title":"Full Name"}},"type":"object","required":["email","password"],"title":"UserRegister"},"ValidationError":{"properties":{"loc":{"items":{"anyOf":[{"type":"string"},{"type":"integer"}]},"type":"array","title":"Location"},"msg":{"type":"string","title":"Message"},"type":{"type":"string","title":"Error Type"},"input":{"title":"Input"},"ctx":{"type":"object","title":"Context"}},"type":"object","required":["loc","msg","type"],"title":"ValidationError"}},"securitySchemes":{"OAuth2PasswordBearer":{"type":"oauth2","flows":{"password":{"scopes":{},"tokenUrl":"/api/v1/login/access-token"}}}}}}